LICENSE
README.md
setup.py
dmte/__init__.py
dmte/lex.py
dmte/style.py
dmte/token.py
dmte_lib.egg-info/PKG-INFO
dmte_lib.egg-info/SOURCES.txt
dmte_lib.egg-info/dependency_links.txt
dmte_lib.egg-info/requires.txt
dmte_lib.egg-info/top_level.txt