Metadata-Version: 2.1
Name: dmte-lib
Version: 0.0.0a0
Summary: dmte
Home-page: https://gitlab.com/dmatryus.sqrt49/dmte
Author: dmatryus
Author-email: dmatryus.sqrt49@yandex.ru
License: MIT
Keywords: TEXT_EDITOR
License-File: LICENSE
